pyltc/__init__.py
pyltc/app.py
pyltc/audioutils.py
pyltc/fields.py
pyltc/frames.py
pyltc/mtc.py
pyltc/tcgen.py
pyltc/tcread.py
pyltc/audio/__init__.py
pyltc/audio/base.py
pyltc/audio/gst_audio.py
pyltc/audio/pygame_audio.py
pyltc/audio/pyjack_audio.py
pyltc/audio/pysimple_audio.py
pyltc/audio/sounddevice_audio.py
python_ltc-0.0.3.dist-info/DESCRIPTION.rst
python_ltc-0.0.3.dist-info/METADATA
python_ltc-0.0.3.dist-info/RECORD
python_ltc-0.0.3.dist-info/WHEEL
python_ltc-0.0.3.dist-info/metadata.json
python_ltc-0.0.3.dist-info/top_level.txt
